owoify/__init__.py
owoify/owoify.py
owoify/structures/__init__.py
owoify/structures/word.py
owoify/utility/__init__.py
owoify/utility/flatten.py
owoify/utility/interleave_arrays.py
owoify/utility/mapping.py
owoify/utility/presets.py
test/__init__.py
test/owoify_test.py
owoify_py-2.1.0.dist-info/LICENSE
owoify_py-2.1.0.dist-info/METADATA
owoify_py-2.1.0.dist-info/WHEEL
owoify_py-2.1.0.dist-info/top_level.txt
owoify_py-2.1.0.dist-info/RECORD
