Metadata-Version: 2.1
Name: owoify-py
Version: 2.1.0
Summary: Turning your worst nightmare into a Python package.
Home-page: https://github.com/deadshot465/owoify-py
Author: Chehui Chou
Author-email: tetsuki.syu1315@gmail.com
Requires-Python: >=3.10
License-File: LICENSE
